wbgapi/__init__.py
wbgapi/data.py
wbgapi/economy.py
wbgapi/economy_coder.py
wbgapi/economy_metadata.py
wbgapi/income.py
wbgapi/lending.py
wbgapi/lookup-data.yaml
wbgapi/region.py
wbgapi/series.py
wbgapi/series_metadata.py
wbgapi/source.py
wbgapi/time.py
wbgapi/topic.py
wbgapi-1.1.2.dist-info/LICENSE.txt
wbgapi-1.1.2.dist-info/METADATA
wbgapi-1.1.2.dist-info/WHEEL
wbgapi-1.1.2.dist-info/top_level.txt
wbgapi-1.1.2.dist-info/RECORD
