Metadata-Version: 2.1
Name: wbgapi
Version: 1.1.2
Summary: wbgapi provides a comprehensive interface to the World Bank's data and metadata APIs
Home-page: https://github.com/tgherzog/wbgapi
Author: Tim Herzog
License: MIT
Platform: UNKNOWN
Classifier: Programming Language :: Python :: 3
Classifier: License :: OSI Approved :: MIT License
Classifier: Operating System :: OS Independent
Classifier: Development Status :: 5 - Production/Stable
Requires-Python: >=3.0
Requires-Dist: requests
Requires-Dist: PyYAML
Requires-Dist: tabulate
